crxsnake/Cogs.py
crxsnake/Errors.py
crxsnake/Misc.py
crxsnake/Reader.py
crxsnake/Tortoise.py
crxsnake/__init__.py
crxsnake/loguru.py
crx_snake-1.2.2.dist-info/METADATA
crx_snake-1.2.2.dist-info/WHEEL
crx_snake-1.2.2.dist-info/top_level.txt
crx_snake-1.2.2.dist-info/RECORD
