Metadata-Version: 2.1
Name: crx-snake
Version: 1.2.2
Summary: A collection of functions for creating Discord bots.
Home-page: https://discord.gg/EEp67FWQDP
Author: CRX-DEV
Author-email: cherniq66@gmail.com
License: MIT License
Requires-Dist: tortoise-orm ==0.21.0
Requires-Dist: disnake ==2.9.2
Requires-Dist: aiofiles ==23.2.1
Requires-Dist: fastenv ==0.5.0
Requires-Dist: loguru ==0.7.2
